Topsis/__init__.py
Topsis/__main__.py
topsis_ansh_102303380-1.0.3.dist-info/licenses/LICENSE
topsis_ansh_102303380-1.0.3.dist-info/METADATA
topsis_ansh_102303380-1.0.3.dist-info/WHEEL
topsis_ansh_102303380-1.0.3.dist-info/entry_points.txt
topsis_ansh_102303380-1.0.3.dist-info/top_level.txt
topsis_ansh_102303380-1.0.3.dist-info/RECORD
