Metadata-Version: 2.4
Name: Topsis-Ansh-102303380
Version: 1.0.3
Summary: A Python implementation of TOPSIS (Technique for Order Preference by Similarity to Ideal Solution)
Author: Ansh Mahajan
Author-email: anshakkimahajan@gmail.com
Requires-Python: >=3.7
License-File: LICENSE
Requires-Dist: pandas
Requires-Dist: numpy
Dynamic: author
Dynamic: author-email
Dynamic: description
Dynamic: description-content-type
Dynamic: license-file
Dynamic: requires-dist
Dynamic: requires-python
Dynamic: summary
